{
  "id": 202,
  "displayName": "Timothy Sturm",
  "username": "Oxymoron290",
  "isBlueVerified": false,
  "followers": 151,
  "following": 628,
  "hitPoints": 20,
  "profilePicUrl": "/pfp/202.jpg",
  "bannerPicUrl": "/banner/202.jpg",
  "fullArtUrl": null,
  "tier": "nanobie",
  "abilityName": "Inescapable Retweeter",
  "abilityDescription": "Automatically shares other people's hot takes with zero original commentary, forever trapped in retweet limbo.",
  "attackName": "Timothy's Echo Chamber",
  "attackDescription": "Slams opponents with an unending barrage of retweets and reposts, proving that originality is overrated in Timothy Sturm's world.",
  "attackType": "psyop",
  "attackDamage": 20,
  "weaknessType": "roast",
  "weaknessAmount": 15,
  "resistType": "psyop",
  "resistAmount": 10,
  "description": "Timothy Sturm has very low personal engagement, mostly retweeting content including a viral political take. His own tweeting is minimal and unoriginal, mostly sharing Tesla updates and some personal milestones, with low follower count (151) and nanobie tier indicating a beginner or low influence account. This inspired the 'Inescapable Retweeter' ability with a sarcastic jab at his unoriginal posting style. The attack mocks his echoing of others rather than creating original content. His resistance to psyop fits his somewhat technical cloud architect profile and consistent reposting of tech/political news, while his weakness to roast reflects vulnerability to criticism for lack of originality. Hit points are assigned low due to nanobie tier and low engagement.",
  "rarity": "Common",
  "holo": false,
  "xId": "174169989",
  "cardType": "normal"
}